{
  "properties": {
    "name": "PROJECT",
    "author": null,
    "company": null,
    "startDate": "2025-12-20",
    "finishDate": "2026-01-01",
    "taskCount": 24,
    "resourceCount": 0,
    "assignmentCount": 0
  },
  "tasks": [
    {
      "id": 1,
      "uniqueID": 26010,
      "name": "PROJECT",
      "outlineNumber": "1",
      "outlineLevel": 1,
      "start": "2025-12-20",
      "finish": "2026-01-01",
      "duration": "204.0h",
      "work": "0.0h",
      "percentComplete": 16.39344262295082,
      "type": "FIXED_UNITS",
      "constraint": "AS_SOON_AS_POSSIBLE",
      "predecessors": []
    },
    {
      "id": 2,
      "uniqueID": 26011,
      "name": "Project #1",
      "outlineNumber": "1.1",
      "outlineLevel": 2,
      "start": "2025-12-20",
      "finish": "2025-12-28",
      "duration": "136.0h",
      "work": "0.0h",
      "percentComplete": 19.047619047619047,
      "type": "FIXED_UNITS",
      "constraint": "AS_SOON_AS_POSSIBLE",
      "predecessors": []
    },
    {
      "id": 3,
      "uniqueID": 101717,
      "name": "Task #1",
      "outlineNumber": "1.1.1",
      "outlineLevel": 3,
      "start": "2025-12-21",
      "finish": "2025-12-21",
      "duration": "0.0h",
      "work": "0.0h",
      "percentComplete": 100,
      "type": "FIXED_UNITS",
      "constraint": "AS_SOON_AS_POSSIBLE",
      "predecessors": []
    },
    {
      "id": 4,
      "uniqueID": 101718,
      "name": "Task #3",
      "outlineNumber": "1.1.2",
      "outlineLevel": 3,
      "start": "2025-12-20",
      "finish": "2025-12-20",
      "duration": "0.0h",
      "work": "0.0h",
      "percentComplete": 100,
      "type": "FIXED_UNITS",
      "constraint": "AS_SOON_AS_POSSIBLE",
      "predecessors": []
    },
    {
      "id": 5,
      "uniqueID": 101719,
      "name": "Task #5",
      "outlineNumber": "1.1.3",
      "outlineLevel": 3,
      "start": "2025-12-20",
      "finish": "2025-12-20",
      "duration": "0.0h",
      "work": "0.0h",
      "percentComplete": 100,
      "type": "FIXED_UNITS",
      "constraint": "AS_SOON_AS_POSSIBLE",
      "predecessors": []
    },
    {
      "id": 6,
      "uniqueID": 26013,
      "name": "Task #2",
      "outlineNumber": "1.1.4",
      "outlineLevel": 3,
      "start": "2025-12-21",
      "finish": "2025-12-28",
      "duration": "119.0h",
      "work": "0.0h",
      "percentComplete": 21.192052980132452,
      "type": "FIXED_UNITS",
      "constraint": "AS_SOON_AS_POSSIBLE",
      "predecessors": []
    },
    {
      "id": 7,
      "uniqueID": 101720,
      "name": "Task #2.1",
      "outlineNumber": "1.1.4.1",
      "outlineLevel": 4,
      "start": "2025-12-21",
      "finish": "2025-12-21",
      "duration": "0.0h",
      "work": "0.0h",
      "percentComplete": 100,
      "type": "FIXED_UNITS",
      "constraint": "AS_SOON_AS_POSSIBLE",
      "predecessors": []
    },
    {
      "id": 8,
      "uniqueID": 101721,
      "name": "Task #2.2",
      "outlineNumber": "1.1.4.2",
      "outlineLevel": 4,
      "start": "2025-12-24",
      "finish": "2025-12-24",
      "duration": "0.0h",
      "work": "0.0h",
      "percentComplete": 100,
      "type": "FIXED_UNITS",
      "constraint": "AS_SOON_AS_POSSIBLE",
      "predecessors": [
        {
          "taskID": 7,
          "taskUniqueID": 101720,
          "taskName": "Task #2.1",
          "type": "FS",
          "lag": "0.0h"
        }
      ]
    },
    {
      "id": 9,
      "uniqueID": 101722,
      "name": "Task #2.3",
      "outlineNumber": "1.1.4.3",
      "outlineLevel": 4,
      "start": "2025-12-28",
      "finish": "2025-12-28",
      "duration": "0.0h",
      "work": "0.0h",
      "percentComplete": 100,
      "type": "FIXED_UNITS",
      "constraint": "AS_SOON_AS_POSSIBLE",
      "predecessors": [
        {
          "taskID": 8,
          "taskUniqueID": 101721,
          "taskName": "Task #2.2",
          "type": "FS",
          "lag": "0.0h"
        }
      ]
    },
    {
      "id": 10,
      "uniqueID": 101723,
      "name": "Task #2.4",
      "outlineNumber": "1.1.4.4",
      "outlineLevel": 4,
      "start": "2025-12-28",
      "finish": "2025-12-28",
      "duration": "0.0h",
      "work": "0.0h",
      "percentComplete": 100,
      "type": "FIXED_UNITS",
      "constraint": "AS_SOON_AS_POSSIBLE",
      "predecessors": [
        {
          "taskID": 9,
          "taskUniqueID": 101722,
          "taskName": "Task #2.3",
          "type": "FS",
          "lag": "0.0h"
        }
      ]
    },
    {
      "id": 11,
      "uniqueID": 26014,
      "name": "Task #4",
      "outlineNumber": "1.1.5",
      "outlineLevel": 3,
      "start": "2025-12-21",
      "finish": "2025-12-21",
      "duration": "0.0h",
      "work": "0.0h",
      "percentComplete": 100,
      "type": "FIXED_UNITS",
      "constraint": "AS_SOON_AS_POSSIBLE",
      "predecessors": []
    },
    {
      "id": 12,
      "uniqueID": 101724,
      "name": "Task #4.1",
      "outlineNumber": "1.1.5.1",
      "outlineLevel": 4,
      "start": "2025-12-21",
      "finish": "2025-12-21",
      "duration": "0.0h",
      "work": "0.0h",
      "percentComplete": 100,
      "type": "FIXED_UNITS",
      "constraint": "AS_SOON_AS_POSSIBLE",
      "predecessors": []
    },
    {
      "id": 13,
      "uniqueID": 101725,
      "name": "Task #4.2",
      "outlineNumber": "1.1.5.2",
      "outlineLevel": 4,
      "start": "2025-12-21",
      "finish": "2025-12-21",
      "duration": "0.0h",
      "work": "0.0h",
      "percentComplete": 100,
      "type": "FIXED_UNITS",
      "constraint": "AS_SOON_AS_POSSIBLE",
      "predecessors": []
    },
    {
      "id": 14,
      "uniqueID": 101726,
      "name": "Task #4.3",
      "outlineNumber": "1.1.5.3",
      "outlineLevel": 4,
      "start": "2025-12-21",
      "finish": "2025-12-21",
      "duration": "0.0h",
      "work": "0.0h",
      "percentComplete": 100,
      "type": "FIXED_UNITS",
      "constraint": "AS_SOON_AS_POSSIBLE",
      "predecessors": []
    },
    {
      "id": 15,
      "uniqueID": 26012,
      "name": "Project #2",
      "outlineNumber": "1.2",
      "outlineLevel": 2,
      "start": "2025-12-20",
      "finish": "2026-01-01",
      "duration": "204.0h",
      "work": "0.0h",
      "percentComplete": 16.39344262295082,
      "type": "FIXED_UNITS",
      "constraint": "AS_SOON_AS_POSSIBLE",
      "predecessors": []
    },
    {
      "id": 16,
      "uniqueID": 26015,
      "name": "Task #1",
      "outlineNumber": "1.2.1",
      "outlineLevel": 3,
      "start": "2025-12-20",
      "finish": "2025-12-21",
      "duration": "17.0h",
      "work": "0.0h",
      "percentComplete": 76.71232876712328,
      "type": "FIXED_UNITS",
      "constraint": "AS_SOON_AS_POSSIBLE",
      "predecessors": []
    },
    {
      "id": 17,
      "uniqueID": 101727,
      "name": "Task #1.1",
      "outlineNumber": "1.2.1.1",
      "outlineLevel": 4,
      "start": "2025-12-20",
      "finish": "2025-12-20",
      "duration": "0.0h",
      "work": "0.0h",
      "percentComplete": 100,
      "type": "FIXED_UNITS",
      "constraint": "AS_SOON_AS_POSSIBLE",
      "predecessors": []
    },
    {
      "id": 18,
      "uniqueID": 101728,
      "name": "Task #1.2",
      "outlineNumber": "1.2.1.2",
      "outlineLevel": 4,
      "start": "2025-12-21",
      "finish": "2025-12-21",
      "duration": "0.0h",
      "work": "0.0h",
      "percentComplete": 100,
      "type": "FIXED_UNITS",
      "constraint": "AS_SOON_AS_POSSIBLE",
      "predecessors": []
    },
    {
      "id": 19,
      "uniqueID": 26016,
      "name": "Task #2",
      "outlineNumber": "1.2.2",
      "outlineLevel": 3,
      "start": "2025-12-29",
      "finish": "2025-12-29",
      "duration": "0.0h",
      "work": "0.0h",
      "percentComplete": 100,
      "type": "FIXED_UNITS",
      "constraint": "AS_SOON_AS_POSSIBLE",
      "predecessors": []
    },
    {
      "id": 20,
      "uniqueID": 101729,
      "name": "Task #2.1",
      "outlineNumber": "1.2.2.1",
      "outlineLevel": 4,
      "start": "2025-12-29",
      "finish": "2025-12-29",
      "duration": "0.0h",
      "work": "0.0h",
      "percentComplete": 100,
      "type": "FIXED_UNITS",
      "constraint": "AS_SOON_AS_POSSIBLE",
      "predecessors": []
    },
    {
      "id": 21,
      "uniqueID": 26017,
      "name": "Task #3",
      "outlineNumber": "1.2.3",
      "outlineLevel": 3,
      "start": "2026-01-01",
      "finish": "2026-01-01",
      "duration": "0.0h",
      "work": "0.0h",
      "percentComplete": 100,
      "type": "FIXED_UNITS",
      "constraint": "AS_SOON_AS_POSSIBLE",
      "predecessors": []
    },
    {
      "id": 22,
      "uniqueID": 101730,
      "name": "Task #3.1",
      "outlineNumber": "1.2.3.1",
      "outlineLevel": 4,
      "start": "2026-01-01",
      "finish": "2026-01-01",
      "duration": "0.0h",
      "work": "0.0h",
      "percentComplete": 100,
      "type": "FIXED_UNITS",
      "constraint": "AS_SOON_AS_POSSIBLE",
      "predecessors": []
    },
    {
      "id": 23,
      "uniqueID": 101731,
      "name": "Task #3.2",
      "outlineNumber": "1.2.3.2",
      "outlineLevel": 4,
      "start": "2026-01-01",
      "finish": "2026-01-01",
      "duration": "0.0h",
      "work": "0.0h",
      "percentComplete": 100,
      "type": "FIXED_UNITS",
      "constraint": "AS_SOON_AS_POSSIBLE",
      "predecessors": []
    },
    {
      "id": 24,
      "uniqueID": 101732,
      "name": "Task #3.3",
      "outlineNumber": "1.2.3.3",
      "outlineLevel": 4,
      "start": "2026-01-01",
      "finish": "2026-01-01",
      "duration": "0.0h",
      "work": "0.0h",
      "percentComplete": 100,
      "type": "FIXED_UNITS",
      "constraint": "AS_SOON_AS_POSSIBLE",
      "predecessors": []
    }
  ],
  "resources": [
    {
      "id": 1,
      "uniqueID": 1,
      "name": "Unassigned",
      "type": "Work",
      "maxUnits": "100%"
    }
  ],
  "assignments": [
    {
      "taskID": 3,
      "taskUniqueID": 101717,
      "taskName": "Task #1",
      "resourceID": 1,
      "resourceUniqueID": 1,
      "resourceName": "Unassigned",
      "units": 100
    },
    {
      "taskID": 4,
      "taskUniqueID": 101718,
      "taskName": "Task #3",
      "resourceID": 1,
      "resourceUniqueID": 1,
      "resourceName": "Unassigned",
      "units": 100
    },
    {
      "taskID": 5,
      "taskUniqueID": 101719,
      "taskName": "Task #5",
      "resourceID": 1,
      "resourceUniqueID": 1,
      "resourceName": "Unassigned",
      "units": 100
    },
    {
      "taskID": 7,
      "taskUniqueID": 101720,
      "taskName": "Task #2.1",
      "resourceID": 1,
      "resourceUniqueID": 1,
      "resourceName": "Unassigned",
      "units": 100
    },
    {
      "taskID": 8,
      "taskUniqueID": 101721,
      "taskName": "Task #2.2",
      "resourceID": 1,
      "resourceUniqueID": 1,
      "resourceName": "Unassigned",
      "units": 100
    },
    {
      "taskID": 9,
      "taskUniqueID": 101722,
      "taskName": "Task #2.3",
      "resourceID": 1,
      "resourceUniqueID": 1,
      "resourceName": "Unassigned",
      "units": 100
    },
    {
      "taskID": 10,
      "taskUniqueID": 101723,
      "taskName": "Task #2.4",
      "resourceID": 1,
      "resourceUniqueID": 1,
      "resourceName": "Unassigned",
      "units": 100
    },
    {
      "taskID": 12,
      "taskUniqueID": 101724,
      "taskName": "Task #4.1",
      "resourceID": 1,
      "resourceUniqueID": 1,
      "resourceName": "Unassigned",
      "units": 100
    },
    {
      "taskID": 13,
      "taskUniqueID": 101725,
      "taskName": "Task #4.2",
      "resourceID": 1,
      "resourceUniqueID": 1,
      "resourceName": "Unassigned",
      "units": 100
    },
    {
      "taskID": 14,
      "taskUniqueID": 101726,
      "taskName": "Task #4.3",
      "resourceID": 1,
      "resourceUniqueID": 1,
      "resourceName": "Unassigned",
      "units": 100
    },
    {
      "taskID": 17,
      "taskUniqueID": 101727,
      "taskName": "Task #1.1",
      "resourceID": 1,
      "resourceUniqueID": 1,
      "resourceName": "Unassigned",
      "units": 100
    },
    {
      "taskID": 18,
      "taskUniqueID": 101728,
      "taskName": "Task #1.2",
      "resourceID": 1,
      "resourceUniqueID": 1,
      "resourceName": "Unassigned",
      "units": 100
    },
    {
      "taskID": 20,
      "taskUniqueID": 101729,
      "taskName": "Task #2.1",
      "resourceID": 1,
      "resourceUniqueID": 1,
      "resourceName": "Unassigned",
      "units": 100
    },
    {
      "taskID": 22,
      "taskUniqueID": 101730,
      "taskName": "Task #3.1",
      "resourceID": 1,
      "resourceUniqueID": 1,
      "resourceName": "Unassigned",
      "units": 100
    },
    {
      "taskID": 23,
      "taskUniqueID": 101731,
      "taskName": "Task #3.2",
      "resourceID": 1,
      "resourceUniqueID": 1,
      "resourceName": "Unassigned",
      "units": 100
    },
    {
      "taskID": 24,
      "taskUniqueID": 101732,
      "taskName": "Task #3.3",
      "resourceID": 1,
      "resourceUniqueID": 1,
      "resourceName": "Unassigned",
      "units": 100
    }
  ]
}